[
  { "time": 500, "text": "Waiting for beat...", "type": "wait" },
  { "time": 9041, "text": "Kim Nam-joon!", "type": "chant" },
  { "time": 10149, "text": "Kim Seok-jin!", "type": "chant" },
  { "time": 11185, "text": "Min Yoon-gi!", "type": "chant" },
  { "time": 12271, "text": "Jung Ho-seok!", "type": "chant" },
  { "time": 13449, "text": "Park Ji-min!", "type": "chant" },
  { "time": 14524, "text": "Kim Tae-hyung!", "type": "chant" },
  { "time": 15664, "text": "Jeon Jung-kook!", "type": "chant" },
  { "time": 16797, "text": "BTS!", "type": "chant" },
  { "time": 21670, "text": "Bo-go sip-da-①", "type": "sing" },
  { "time": 26147, "text": "Bo-go sip-da-②", "type": "sing" },
  { "time": 36514, "text": "Gyeo-ul ppun-i-ya", "type": "sing" },
  { "time": 38195, "text": "Gyeo-ul-i wa", "type": "sing" },
  { "time": 42628, "text": "Seol-guk-yeol-cha", "type": "sing" },
  { "time": 81688, "text": "(Bo-go sip-da)-①", "type": "sing" },
  { "time": 86076, "text": "(Bo-go sip-da)-②", "type": "sing" },
  { "time": 99534, "text": "(Neol bo-ge doel-kka)", "type": "sing" },
  { "time": 104050, "text": "(Man-na-ge doel-kka)", "type": "sing" },
  { "time": 127446, "text": "(Ni-ga byeon-han geon-ji)", "type": "sing" },
  { "time": 128956, "text": "(Nae-ga byeon-han geon-ji)", "type": "sing" },
  { "time": 159000, "text": "", "type": "sakura_start" },
  { "time": 171201, "text": "(Bo-go sip-da)-①", "type": "sing" },
  { "time": 175919, "text": "(Bo-go sip-da)-②", "type": "sing" },
  { "time": 189222, "text": "(Neol bo-ge doel-kka)", "type": "sing" },
  { "time": 193764, "text": "(Man-na-ge doel-kka)", "type": "sing" },
  { "time": 200802, "text": "SCREAM!", "type": "scream" },
  { "time": 225157, "text": "(Bo-go sip-da)-①", "type": "sing" },
  { "time": 229495, "text": "(Bo-go sip-da)-②", "type": "sing" },
  { "time": 243144, "text": "(Man-na-reo gal-ge)", "type": "sing" },
  { "time": 247625, "text": "(De-ri-reo gal-ge)", "type": "sing" },
  { "time": 271894, "text": "(Live) wo wo wo ~~", "type": "wave" },
  { "time": 271900, "text": "", "type": "sakura_stop" }
]
